{
  "productName": "April Dashawn Jordan Character Deck",
  "productBrand": "April Skateboards",
  "productType": "products",
  "cloudinaryUrl": "https://res.cloudinary.com/dxgyuy0iu/image/upload/v1746415631/ldjsonbuild/xn4qgmhcmiqtstkvee8h.webp",
  "imageWidth": 200,
  "imageHeight": 200,
  "updated": 1746544882,
  "productVendorUrl": "https://skateparkoftampa.com/products/april-skateboards-dashawn-jordan-character-deck?variant=51152592339217",
  "productPrices": [
    {
      "spot": "72.00",
      "url": "https://skateparkoftampa.com",
      "productVendorUrl": "https://skateparkoftampa.com/products/april-skateboards-dashawn-jordan-character-deck?variant=51152592339217"
    }
  ]
}