{
  "productName": "DGK Jack Curtin Thizz Deck",
  "productBrand": "DGK",
  "productType": "products",
  "cloudinaryUrl": "https://res.cloudinary.com/dxgyuy0iu/image/upload/v1746414755/ldjsonbuild/cc3e1jqpsi2hbwvphgdh.webp",
  "imageWidth": 200,
  "imageHeight": 200,
  "updated": 1746544882,
  "productVendorUrl": "https://skateparkoftampa.com/products/dgk-jack-curtin-thizz-deck?variant=51297453670673",
  "productPrices": [
    {
      "spot": "70.00",
      "url": "https://skateparkoftampa.com",
      "productVendorUrl": "https://skateparkoftampa.com/products/dgk-jack-curtin-thizz-deck?variant=51297453670673"
    }
  ]
}