{
  "productName": "Neowm Deck",
  "productBrand": "Tactics",
  "productType": "Skateboard Decks",
  "cloudinaryUrl": "https://res.cloudinary.com/dxgyuy0iu/image/upload/v1746395552/ldjsonbuild/gqrnvgastgsrtam8y5bi.webp",
  "imageWidth": 78,
  "imageHeight": 291,
  "updated": 1746544882,
  "productVendorUrl": "https://www.tactics.com/tactics/neowm-skateboard-deck/orange",
  "productPrices": [
    {
      "tactics": "44.95",
      "url": "https://www.tactics.com",
      "productVendorUrl": "https://www.tactics.com/tactics/neowm-skateboard-deck/orange"
    }
  ]
}