{
  "productName": "Reynolds Here To Stay Deck",
  "productBrand": "Baker",
  "productType": "Skateboard Decks",
  "cloudinaryUrl": "https://res.cloudinary.com/dxgyuy0iu/image/upload/v1746402256/ldjsonbuild/uq4tmhe0kdpuq7bek6yk.webp",
  "imageWidth": 78,
  "imageHeight": 291,
  "updated": 1746544882,
  "productVendorUrl": "https://www.tactics.com/baker/reynolds-here-to-stay-838-skateboard-deck",
  "productPrices": [
    {
      "tactics": "73.95",
      "url": "https://www.tactics.com",
      "productVendorUrl": "https://www.tactics.com/baker/reynolds-here-to-stay-838-skateboard-deck"
    }
  ]
}