{
  "productName": "Cortina Lil Dre Signature Bearings",
  "productBrand": "Cortina",
  "productType": "products",
  "cloudinaryUrl": "https://res.cloudinary.com/dxgyuy0iu/image/upload/v1746413681/ldjsonbuild/douhb29rgdpwulfjtdmi.webp",
  "imageWidth": 200,
  "imageHeight": 200,
  "updated": 1746544876,
  "productVendorUrl": "https://skateparkoftampa.com/products/cortina-lil-dre-signature-bearings-90577?variant=48246396944657",
  "productPrices": [
    {
      "spot": "26.0",
      "url": "https://skateparkoftampa.com",
      "productVendorUrl": "https://skateparkoftampa.com/products/cortina-lil-dre-signature-bearings-90577?variant=48246396944657"
    }
  ]
}