{
  "productName": "Sure-Grip Grip + Dip Hybrid Wheels 84A, 59mm, 8-Pack",
  "productBrand": "Sure-Grip",
  "productType": "sure grip grip dip hybrid wheels 84a 59mm 8 pack",
  "cloudinaryUrl": "https://res.cloudinary.com/dxgyuy0iu/image/upload/v1746469049/ldjsonbuild/cxbl5jd5wwfa05tilfa3.webp",
  "imageWidth": 200,
  "imageHeight": 200,
  "updated": 1746569739,
  "productVendorUrl": "https://medusaskates.com/sure-grip-grip-dip-hybrid-wheels-84a-59mm-8-pack/",
  "productPrices": [
    {
      "medusaskates": "69.99",
      "url": "https://medusaskates.com",
      "productVendorUrl": "https://medusaskates.com/sure-grip-grip-dip-hybrid-wheels-84a-59mm-8-pack/"
    }
  ]
}