{
  "productName": "HPF Standard Bushings",
  "productBrand": "Venom",
  "productType": "Truck Accessories",
  "cloudinaryUrl": "https://res.cloudinary.com/dxgyuy0iu/image/upload/v1746392007/ldjsonbuild/npq3tzppdmneek7cz7gn.webp",
  "imageWidth": 200,
  "imageHeight": 200,
  "updated": 1746544876,
  "productVendorUrl": "https://www.tactics.com/venom/hpf-standard-bushings/blue-78a",
  "productPrices": [
    {
      "tactics": "8.95",
      "url": "https://www.tactics.com",
      "productVendorUrl": "https://www.tactics.com/venom/hpf-standard-bushings/blue-78a"
    }
  ]
}