{
  "productName": "Antik Skyhawk Only",
  "productBrand": "Antik",
  "productType": "antik skyhawk boot only",
  "cloudinaryUrl": "https://res.cloudinary.com/dxgyuy0iu/image/upload/v1746468303/ldjsonbuild/xnbkiylfmey6pzbusyzf.webp",
  "imageWidth": 200,
  "imageHeight": 200,
  "updated": 1746569735,
  "productVendorUrl": "https://medusaskates.com/antik-skyhawk-boot-only/",
  "productPrices": [
    {
      "medusaskates": "149",
      "url": "https://medusaskates.com",
      "productVendorUrl": "https://medusaskates.com/antik-skyhawk-boot-only/"
    },
    {
      "derbywarehouse": "149.00",
      "url": "https://www.derbywarehouse.com",
      "productVendorUrl": "https://www.derbywarehouse.com/Antik_Skyhawk/descpage-ASH23.html"
    },
    {
      "riedell": "149.00",
      "url": "https://roller.riedellskates.com",
      "productVendorUrl": "https://roller.riedellskates.com/Product/boot-antik-skyhawk"
    }
  ]
}