{
  "productName": "Bont Wide Skate Park Grind Trucks",
  "productBrand": "Bont",
  "productType": "bont wide skate park grind trucks set of 4",
  "cloudinaryUrl": "https://res.cloudinary.com/dxgyuy0iu/image/upload/v1746468440/ldjsonbuild/fjgx1eukolzescn0gndc.webp",
  "imageWidth": 200,
  "imageHeight": 200,
  "updated": 1746569738,
  "productVendorUrl": "https://medusaskates.com/bont-wide-skate-park-grind-trucks-set-of-4/",
  "productPrices": [
    {
      "medusaskates": "79.99",
      "url": "https://medusaskates.com",
      "productVendorUrl": "https://medusaskates.com/bont-wide-skate-park-grind-trucks-set-of-4/"
    }
  ]
}