{
  "productName": "Mini logo Trucks 8.00",
  "productBrand": "mini logo",
  "productType": "",
  "cloudinaryUrl": "https://res.cloudinary.com/dxgyuy0iu/image/upload/v1747414659/metacrawler/ini7czffkytkpt6fqqvz.webp",
  "imageWidth": 200,
  "imageHeight": 200,
  "updated": 1747418564,
  "productVendorUrl": "https://minilogoskateboards.com/mini-logo-trucks-8-0-raw-set-of-2",
  "productPrices": [
    {
      "minilogo": "42.95",
      "url": "https://minilogoskateboards.com",
      "productVendorUrl": "https://minilogoskateboards.com/mini-logo-trucks-8-0-raw-set-of-2"
    }
  ]
}