{
  "productName": "Thunder Ishod Wair Dawg Team Hollow Truck",
  "productBrand": "Thunder",
  "productType": "products",
  "cloudinaryUrl": "https://res.cloudinary.com/dxgyuy0iu/image/upload/v1746416800/ldjsonbuild/gdeus0zes6safyf6snjg.webp",
  "imageWidth": 200,
  "imageHeight": 200,
  "updated": 1746544886,
  "productVendorUrl": "https://skateparkoftampa.com/products/thunder-ishod-wair-dawg-team-hollow-truck-94662?variant=48246937714961",
  "productPrices": [
    {
      "spot": "23.0",
      "url": "https://skateparkoftampa.com",
      "productVendorUrl": "https://skateparkoftampa.com/products/thunder-ishod-wair-dawg-team-hollow-truck-94662?variant=48246937714961"
    }
  ]
}